coredis/__init__.py
coredis/_enum.py
coredis/_json.py
coredis/_packer.py
coredis/_protocols.py
coredis/_py_311_typing.py
coredis/_py_312_typing.py
coredis/_sidecar.py
coredis/_utils.py
coredis/_version.py
coredis/_version.pyi
coredis/cache.py
coredis/config.py
coredis/connection.py
coredis/constants.py
coredis/credentials.py
coredis/exceptions.py
coredis/globals.py
coredis/parser.py
coredis/pipeline.py
coredis/py.typed
coredis/retry.py
coredis/sentinel.py
coredis/stream.py
coredis/tokens.py
coredis/typing.py
coredis/client/__init__.py
coredis/client/basic.py
coredis/client/cluster.py
coredis/commands/__init__.py
coredis/commands/_key_spec.py
coredis/commands/_utils.py
coredis/commands/_validators.py
coredis/commands/_wrappers.py
coredis/commands/bitfield.py
coredis/commands/constants.py
coredis/commands/core.py
coredis/commands/function.py
coredis/commands/monitor.py
coredis/commands/pubsub.py
coredis/commands/request.py
coredis/commands/script.py
coredis/commands/sentinel.py
coredis/experimental/__init__.py
coredis/modules/__init__.py
coredis/modules/autocomplete.py
coredis/modules/base.py
coredis/modules/filters.py
coredis/modules/graph.py
coredis/modules/json.py
coredis/modules/search.py
coredis/modules/timeseries.py
coredis/modules/response/__init__.py
coredis/modules/response/types.py
coredis/modules/response/_callbacks/__init__.py
coredis/modules/response/_callbacks/autocomplete.py
coredis/modules/response/_callbacks/graph.py
coredis/modules/response/_callbacks/json.py
coredis/modules/response/_callbacks/search.py
coredis/modules/response/_callbacks/timeseries.py
coredis/pool/__init__.py
coredis/pool/basic.py
coredis/pool/cluster.py
coredis/pool/nodemanager.py
coredis/recipes/__init__.py
coredis/recipes/credentials/__init__.py
coredis/recipes/credentials/iam_provider.py
coredis/recipes/locks/__init__.py
coredis/recipes/locks/extend.lua
coredis/recipes/locks/lua_lock.py
coredis/recipes/locks/release.lua
coredis/response/__init__.py
coredis/response/_utils.py
coredis-5.6.0.dist-info/METADATA
coredis-5.6.0.dist-info/WHEEL
coredis-5.6.0.dist-info/licenses/LICENSE
coredis-5.6.0.dist-info/RECORD
