Metadata-Version: 2.4
Name: coredis
Version: 5.6.0
Summary: Python async client for Redis key-value store
Project-URL: Homepage, https://github.com/alisaifee/coredis
Project-URL: Source, https://github.com/alisaifee/coredis
Project-URL: Changelog, https://github.com/alisaifee/coredis/releases
Project-URL: Documentation, https://coredis.readthedocs.org
Author-email: Ali-Akber Saifee <ali@indydevs.org>
Maintainer-email: Ali-Akber Saifee <ali@indydevs.org>
License-Expression: MIT
License-File: LICENSE
Keywords: Redis,asyncio,key-value store
Classifier: Development Status :: 5 - Production/Stable
Classifier: Intended Audience :: Developers
Classifier: Operating System :: OS Independent
Classifier: Programming Language :: Python
Classifier: Programming Language :: Python :: 3.10
Classifier: Programming Language :: Python :: 3.11
Classifier: Programming Language :: Python :: 3.12
Classifier: Programming Language :: Python :: 3.13
Classifier: Programming Language :: Python :: 3.14
Classifier: Programming Language :: Python :: Implementation :: PyPy
Requires-Python: >=3.10
Requires-Dist: async-timeout<6,>4
Requires-Dist: beartype>=0.20
Requires-Dist: deprecated>=1.2
Requires-Dist: packaging<26,>=21
Requires-Dist: pympler<2,>1
Requires-Dist: typing-extensions>=4.13
Provides-Extra: recipes
Requires-Dist: aiobotocore>=2.15.2; extra == 'recipes'
Requires-Dist: asyncache>=0.3.1; extra == 'recipes'
